README.md
setup.py
afrodite/modulo.py
afrodite.egg-info/PKG-INFO
afrodite.egg-info/SOURCES.txt
afrodite.egg-info/dependency_links.txt
afrodite.egg-info/requires.txt
afrodite.egg-info/top_level.txt