Metadata-Version: 2.1
Name: afrodite
Version: 0.0.1
Summary: Exemplo de pacote PyPI
Home-page: https://github.com/adsmaicon
Author: Maicon Carvalho
Author-email: caiocarneloz@gmail.com
License: MIT License
Keywords: Pacote
Platform: UNKNOWN
